README.md
setup.cfg
setup.py
quasar_api/__init__.py
quasar_api/api.py
quasar_api/errors.py
quasar_api/schemas.py
quasar_api/utils.py
yandex_quasar.egg-info/PKG-INFO
yandex_quasar.egg-info/SOURCES.txt
yandex_quasar.egg-info/dependency_links.txt
yandex_quasar.egg-info/not-zip-safe
yandex_quasar.egg-info/requires.txt
yandex_quasar.egg-info/top_level.txt