Metadata-Version: 2.1
Name: yandex-quasar
Version: 0.1
Summary: Yandex Quasar API
Home-page: https://github.com/btfspace/yandex-quasar
Author-email: me@biteof.space
License: UNKNOWN
Platform: UNKNOWN
Classifier: Programming Language :: Python :: 3
Classifier: License :: OSI Approved :: MIT License
Classifier: Operating System :: OS Independent
